provider_dedupe/__init__.py
provider_dedupe/cli/__init__.py
provider_dedupe/cli/main.py
provider_dedupe/core/__init__.py
provider_dedupe/core/config.py
provider_dedupe/core/deduplicator.py
provider_dedupe/core/exceptions.py
provider_dedupe/models/__init__.py
provider_dedupe/models/provider.py
provider_dedupe/services/__init__.py
provider_dedupe/services/data_loader.py
provider_dedupe/services/data_quality.py
provider_dedupe/services/output_generator.py
provider_dedupe/utils/__init__.py
provider_dedupe/utils/logging.py
provider_dedupe/utils/normalization.py
provider_dedupe-1.0.0.dist-info/METADATA
provider_dedupe-1.0.0.dist-info/WHEEL
provider_dedupe-1.0.0.dist-info/entry_points.txt
provider_dedupe-1.0.0.dist-info/top_level.txt
provider_dedupe-1.0.0.dist-info/RECORD
