Metadata-Version: 2.4
Name: provider-dedupe
Version: 1.0.0
Summary: Command-line tool for deduplicating healthcare provider data using probabilistic record linkage
Author: Taylor Hickman
License: MIT
Project-URL: Homepage, https://github.com/taylor-hickman/provider_dedupe
Project-URL: Repository, https://github.com/taylor-hickman/provider_dedupe
Project-URL: Issues, https://github.com/taylor-hickman/provider_dedupe/issues
Keywords: deduplication,record-linkage,healthcare,data-quality,splink
Classifier: Development Status :: 4 - Beta
Classifier: Intended Audience :: Healthcare Industry
Classifier: License :: OSI Approved :: MIT License
Classifier: Programming Language :: Python :: 3
Classifier: Programming Language :: Python :: 3.9
Classifier: Programming Language :: Python :: 3.10
Classifier: Programming Language :: Python :: 3.11
Classifier: Programming Language :: Python :: 3.12
Classifier: Topic :: Scientific/Engineering :: Information Analysis
Classifier: Topic :: Software Development :: Libraries :: Python Modules
Requires-Python: >=3.9
Requires-Dist: pandas<3.0.0,>=1.5.0
Requires-Dist: numpy<3.0.0,>=1.23.0
Requires-Dist: click<9.0.0,>=8.0.0
Requires-Dist: splink>=3.9.0
Requires-Dist: duckdb>=0.8.0
Requires-Dist: python-dateutil>=2.8.0
Requires-Dist: text2num>=2.0.0
Requires-Dist: pydantic>=2.0.0
Requires-Dist: pydantic-settings>=2.0.0
Requires-Dist: structlog>=23.0.0
Requires-Dist: python-dotenv>=1.0.0
Provides-Extra: dev
Requires-Dist: pytest>=7.0.0; extra == "dev"
Requires-Dist: pytest-cov>=4.0.0; extra == "dev"
Requires-Dist: pytest-mock>=3.10.0; extra == "dev"
Requires-Dist: pytest-asyncio>=0.21.0; extra == "dev"
Requires-Dist: black>=23.0.0; extra == "dev"
Requires-Dist: isort>=5.12.0; extra == "dev"
Requires-Dist: flake8>=6.0.0; extra == "dev"
Requires-Dist: mypy>=1.0.0; extra == "dev"
Requires-Dist: pre-commit>=3.0.0; extra == "dev"
Requires-Dist: faker>=18.0.0; extra == "dev"
Requires-Dist: bandit>=1.7.0; extra == "dev"
Requires-Dist: safety>=2.0.0; extra == "dev"
Requires-Dist: matplotlib>=3.5.0; extra == "dev"
Requires-Dist: seaborn>=0.12.0; extra == "dev"
Provides-Extra: viz
Requires-Dist: matplotlib>=3.5.0; extra == "viz"
Requires-Dist: seaborn>=0.12.0; extra == "viz"
Requires-Dist: plotly>=5.0.0; extra == "viz"
Provides-Extra: excel
Requires-Dist: openpyxl>=3.0.0; extra == "excel"
Provides-Extra: parquet
Requires-Dist: pyarrow>=10.0.0; extra == "parquet"
Provides-Extra: all
Requires-Dist: provider-dedupe[dev,excel,parquet,viz]; extra == "all"
